allos/__init__.py
allos/_modidx.py
allos/core.py
allos/gene_report.py
allos/plot_transcripts.py
allos-0.0.2.dist-info/LICENSE
allos-0.0.2.dist-info/METADATA
allos-0.0.2.dist-info/WHEEL
allos-0.0.2.dist-info/entry_points.txt
allos-0.0.2.dist-info/top_level.txt
allos-0.0.2.dist-info/RECORD
