Metadata-Version: 2.1
Name: allos
Version: 0.0.2
Summary: Storage and visualization of long read based single cell datasets
Home-page: https://github.com/cobioda/allos
Author: Anna Diamant
Author-email: diamant.anya@gmail.com
License: Apache Software License 2.0
Keywords: nbdev jupyter notebook python
Classifier: Development Status :: 4 - Beta
Classifier: Intended Audience :: Developers
Classifier: Natural Language :: English
Classifier: Programming Language :: Python :: 3.7
Classifier: Programming Language :: Python :: 3.8
Classifier: Programming Language :: Python :: 3.9
Classifier: Programming Language :: Python :: 3.10
Classifier: License :: OSI Approved :: Apache Software License
Requires-Python: >=3.7
License-File: LICENSE
Requires-Dist: scanpy
Requires-Dist: scipy
Requires-Dist: muon
Requires-Dist: anndata
Requires-Dist: matplotlib
Requires-Dist: seaborn
Requires-Dist: requests
Requires-Dist: patchworklib
Requires-Dist: numpy
Requires-Dist: pandas
Requires-Dist: fastcore
Provides-Extra: dev
